Medeina/CompressedWebStore.zip
Medeina/MedeinaCumulativeApplication.py
Medeina/PollinationWeb.py
Medeina/TrophicWeb.py
Medeina/Web.py
Medeina/__init__.py
Medeina/common.py
Medeina/config.py
Medeina/dataCleaning.py
Medeina/dataFormatReaders.py
Medeina/exportTools.py
Medeina/externalAPIs.py
Medeina/filterFunctions.py
Medeina/interactionParser.py
Medeina/parsingFunctionality.py
Medeina/webStore.py
Medeina-2.1.dist-info/LICENSE.txt
Medeina-2.1.dist-info/METADATA
Medeina-2.1.dist-info/WHEEL
Medeina-2.1.dist-info/top_level.txt
Medeina-2.1.dist-info/RECORD
