Metadata-Version: 2.1
Name: Medeina
Version: 2.1
Summary: A automated solution for building of cumulative interacion web
Home-page: https://github.com/Daniel-Davies/Medeina
Author: Daniel Davies
Author-email: dd16785@bristol.ac.uk
License: UNKNOWN
Keywords: Food Webs,Species networks,Cumulative Networks
Platform: UNKNOWN
Classifier: Programming Language :: Python :: 3
Classifier: License :: OSI Approved :: MIT License
Classifier: Operating System :: OS Independent
Requires-Dist: pycountry
Requires-Dist: taxon-parser
Requires-Dist: networkx
Requires-Dist: numpy
Requires-Dist: msgpack
Requires-Dist: EcoNameTranslator
Requires-Dist: requests
Requires-Dist: pandas
